aiocrontab/__init__.py
aiocrontab/core.py
aiocrontab-0.1.2.dist-info/LICENSE
aiocrontab-0.1.2.dist-info/METADATA
aiocrontab-0.1.2.dist-info/WHEEL
aiocrontab-0.1.2.dist-info/RECORD
