Metadata-Version: 2.3
Name: aiocrontab
Version: 0.1.2
Summary: Crontab implementation in asyncio 
License: MIT
Author: Bhavesh Praveen
Author-email: bhavespraveen.dev@gmail.com
Requires-Python: >=3.12.1,<4.0.0
Classifier: License :: OSI Approved :: MIT License
Classifier: Programming Language :: Python :: 3
Classifier: Programming Language :: Python :: 3.13
Requires-Dist: croniter (==6.0.0)
Requires-Dist: typing_extensions ; python_full_version >= "3.12.1" and python_full_version < "3.13.0"
